{
  "_static": {
    "generator": {
      "name":  "@globus/static-data-portal"
    }
  },
  "data": {
    "version": "1.0.0",
    "attributes": {
      "content": {
        "title": "Meta Demo",
        "privacy_policy": "This is an example privacy policy – you should replace this with your own policy.",
        "terms_of_service": "This is an example terms of service – you should replace this with your own terms."
      },
      "globus": {
        "application": {
          "client_id": "dbb3392b-4f6e-42e6-9dc0-29272e033a76"
      },
        "transfer": {
          "collection_id": "996383e6-0c85-4339-a5ea-c3cd855c2692"
        }
      }
    }
  }
}
